{"ragender": "2.Woman", "agey": 61.0, "shlt": "2.Very good", "hibpe": "0.no", "diabe": "0.no", "cancre": "0.no", "respe": "1.yes", "hrtatte": "0.no", "stroke": "0.no", "arthre": "0.no", "vigact": "1.Yes", "smokev": "0.No", "smoken": "0.No", "cholst": "1.Yes", "breast": "1.Yes", "mammog": "0.No", "papsm": "1.Yes", "prost": "", "dresshlp": "", "walkhlp": "", "bathehlp": "", "eathlp": "", "bedhlp": "", "toilethlp": "", "mealhlp": "", "shophlp": "", "medhlp": "", "moneyhlp": "", "walkre": "", "bede": "", "racany": "", "ricany": "", "flusht": "1.Yes", "hearte": "", "bmi": "", "smokef": 0.0, "strtsmok": "", "quitsmok": ""}